evo/data_converters/duf/__init__.py
evo/data_converters/duf/duf_reader_context.py
evo/data_converters/duf/utils.py
evo/data_converters/duf/xprops.py
evo/data_converters/duf/common/__init__.py
evo/data_converters/duf/common/consts.py
evo/data_converters/duf/common/deswik_types.py
evo/data_converters/duf/common/duf_wrapper.py
evo/data_converters/duf/common/setup_deswik_lib_bindings.py
evo/data_converters/duf/importer/__init__.py
evo/data_converters/duf/importer/duf_polyface_to_evo.py
evo/data_converters/duf/importer/duf_polyline_to_evo.py
evo/data_converters/duf/importer/duf_to_evo.py
evo/data_converters/duf/importer/utils.py
evo_data_converters_duf-0.2.1.dist-info/METADATA
evo_data_converters_duf-0.2.1.dist-info/WHEEL
evo_data_converters_duf-0.2.1.dist-info/licenses/LICENSE.md
evo_data_converters_duf-0.2.1.dist-info/RECORD
