Metadata-Version: 2.4
Name: evo-data-converters-duf
Version: 0.2.1
Summary: Python data converters for Deswik DUF to Evo geoscience objects
Author-email: Seequent <support@seequent.com>
License-File: LICENSE.md
Classifier: Operating System :: Microsoft :: Windows
Requires-Python: >=3.10
Requires-Dist: evo-data-converters-common>=0.3.1
Requires-Dist: pythonnet<3.1.0,>=3.0.5
